aiverify_blur_corruptions/__init__.py
aiverify_blur_corruptions/__main__.py
aiverify_blur_corruptions/algo.meta.json
aiverify_blur_corruptions/algo.py
aiverify_blur_corruptions/algo_init.py
aiverify_blur_corruptions/input.schema.json
aiverify_blur_corruptions/output.schema.json
aiverify_blur_corruptions/plugin_init.py
aiverify_blur_corruptions/utils/__init__.py
aiverify_blur_corruptions/utils/blur.py
aiverify_blur_corruptions-2.1.0.dist-info/METADATA
aiverify_blur_corruptions-2.1.0.dist-info/WHEEL
aiverify_blur_corruptions-2.1.0.dist-info/entry_points.txt
aiverify_blur_corruptions-2.1.0.dist-info/licenses/AUTHORS.rst
aiverify_blur_corruptions-2.1.0.dist-info/licenses/LICENSE
aiverify_blur_corruptions-2.1.0.dist-info/licenses/NOTICE.md
aiverify_blur_corruptions-2.1.0.dist-info/RECORD
